{
  "menuSubItems": [],
  "subMenuChoices": [],
  "menuSubItemGroups": [
    {
      "menuSubItemGroupId": 1736,
      "groupName": "*Option Full List_NO MILK (2)",
      "displayName": "Extra Toppings",
      "position": 2,
      "maxSelect": 100,
      "minSelect": 0,
      "isSubstitute": false,
      "isPizza": false,
      "showHalf": false,
      "showDefaultItemName": false,
      "sortBy": "Alpha",
      "isActive": true,
      "groupPrices": [
        {
          "menuSubItemGroupPriceId": 12043,
          "menuSubItemId": 10940,
          "menuSubItemGroupMenuSubItemGroupId": 1736,
          "price": 0.5,
          "halfPrice": 0,
          "position": 0,
          "isActive": false,
          "isDefault": false,
          "menuSubItem": {
            "menuSubItemId": 10940,
            "name": "Agar Boba ",
            "price": 0,
            "displayDescription": "Agar Boba ",
            "restaurantId": 55,
            "externalId": "3000036",
            "itemTypeId": 2,
            "isActive": false,
            "itemTypeName": "Option"
          }
        },
        {
          "menuSubItemGroupPriceId": 12044,
          "menuSubItemId": 10941,
          "menuSubItemGroupMenuSubItemGroupId": 1736,
          "price": 0.75,
          "halfPrice": 0,
          "position": 0,
          "isActive": false,
          "isDefault": false,
          "menuSubItem": {
            "menuSubItemId": 10941,
            "name": "Aloe Vera",
            "price": 0.5,
            "displayDescription": "Aloe Vera",
            "restaurantId": 55,
            "externalId": "3000016",
            "itemTypeId": 2,
            "isActive": false,
            "itemTypeName": "Option"
          }
        },
        {
          "menuSubItemGroupPriceId": 12045,
          "menuSubItemId": 10933,
          "menuSubItemGroupMenuSubItemGroupId": 1736,
          "price": 0.5,
          "halfPrice": 0,
          "position": 0,
          "isActive": false,
          "isDefault": false,
          "menuSubItem": {
            "menuSubItemId": 10933,
            "name": "Boba",
            "price": 0.5,
            "displayDescription": "Boba",
            "restaurantId": 55,
            "externalId": "3000009",
            "itemTypeId": 2,
            "isActive": false,
            "itemTypeName": "Option"
          }
        },
        {
          "menuSubItemGroupPriceId": 12046,
          "menuSubItemId": 10959,
          "menuSubItemGroupMenuSubItemGroupId": 1736,
          "price": 0.5,
          "halfPrice": 0,
          "position": 0,
          "isActive": false,
          "isDefault": false,
          "menuSubItem": {
            "menuSubItemId": 10959,
            "name": "Chia Seed",
            "price": 0,
            "displayDescription": "Chia Seed",
            "restaurantId": 55,
            "externalId": "3000035",
            "itemTypeId": 2,
            "isActive": false,
            "itemTypeName": "Option"
          }
        },
        {
          "menuSubItemGroupPriceId": 12047,
          "menuSubItemId": 10948,
          "menuSubItemGroupMenuSubItemGroupId": 1736,
          "price": 0.5,
          "halfPrice": 0,
          "position": 0,
          "isActive": false,
          "isDefault": false,
          "menuSubItem": {
            "menuSubItemId": 10948,
            "name": "Coffee Jelly",
            "price": 0.5,
            "displayDescription": "Coffee Jelly",
            "restaurantId": 55,
            "externalId": "3000015",
            "itemTypeId": 2,
            "isActive": false,
            "itemTypeName": "Option"
          }
        },
        {
          "menuSubItemGroupPriceId": 12048,
          "menuSubItemId": 10939,
          "menuSubItemGroupMenuSubItemGroupId": 1736,
          "price": 0.5,
          "halfPrice": 0,
          "position": 0,
          "isActive": false,
          "isDefault": false,
          "menuSubItem": {
            "menuSubItemId": 10939,
            "name": "Egg Pudding",
            "price": 0.5,
            "displayDescription": "Egg Pudding",
            "restaurantId": 55,
            "externalId": "3000010",
            "itemTypeId": 2,
            "isActive": false,
            "itemTypeName": "Option"
          }
        },
        {
          "menuSubItemGroupPriceId": 12049,
          "menuSubItemId": 10943,
          "menuSubItemGroupMenuSubItemGroupId": 1736,
          "price": 0.5,
          "halfPrice": 0,
          "position": 0,
          "isActive": false,
          "isDefault": false,
          "menuSubItem": {
            "menuSubItemId": 10943,
            "name": "Grass Jelly",
            "price": 0.5,
            "displayDescription": "Grass Jelly",
            "restaurantId": 55,
            "externalId": "3000012",
            "itemTypeId": 2,
            "isActive": false,
            "itemTypeName": "Option"
          }
        },
        {
          "menuSubItemGroupPriceId": 12050,
          "menuSubItemId": 10944,
          "menuSubItemGroupMenuSubItemGroupId": 1736,
          "price": 0.5,
          "halfPrice": 0,
          "position": 0,
          "isActive": false,
          "isDefault": false,
          "menuSubItem": {
            "menuSubItemId": 10944,
            "name": "Litchi Jelly",
            "price": 0.5,
            "displayDescription": "Litchi Jelly",
            "restaurantId": 55,
            "externalId": "3000014",
            "itemTypeId": 2,
            "isActive": false,
            "itemTypeName": "Option"
          }
        },
        {
          "menuSubItemGroupPriceId": 12051,
          "menuSubItemId": 10935,
          "menuSubItemGroupMenuSubItemGroupId": 1736,
          "price": 0.5,
          "halfPrice": 0,
          "position": 0,
          "isActive": false,
          "isDefault": false,
          "menuSubItem": {
            "menuSubItemId": 10935,
            "name": "Mango Jelly",
            "price": 0.5,
            "displayDescription": "Mango Jelly",
            "restaurantId": 55,
            "externalId": "3000031",
            "itemTypeId": 2,
            "isActive": false,
            "itemTypeName": "Option"
          }
        },
        {
          "menuSubItemGroupPriceId": 12052,
          "menuSubItemId": 11008,
          "menuSubItemGroupMenuSubItemGroupId": 1736,
          "price": 0.75,
          "halfPrice": 0,
          "position": 0,
          "isActive": false,
          "isDefault": false,
          "menuSubItem": {
            "menuSubItemId": 11008,
            "name": "Mango Popping Boba",
            "price": 0,
            "displayDescription": "Mango Popping Boba",
            "restaurantId": 55,
            "itemTypeId": 2,
            "isActive": true,
            "itemTypeName": "Option"
          }
        },
        {
          "menuSubItemGroupPriceId": 12053,
          "menuSubItemId": 10952,
          "menuSubItemGroupMenuSubItemGroupId": 1736,
          "price": 0.5,
          "halfPrice": 0,
          "position": 0,
          "isActive": false,
          "isDefault": false,
          "menuSubItem": {
            "menuSubItemId": 10952,
            "name": "Mango Pudding",
            "price": 0.5,
            "displayDescription": "Mango Pudding",
            "restaurantId": 55,
            "externalId": "3000011",
            "itemTypeId": 2,
            "isActive": false,
            "itemTypeName": "Option"
          }
        },
        {
          "menuSubItemGroupPriceId": 12054,
          "menuSubItemId": 10951,
          "menuSubItemGroupMenuSubItemGroupId": 1736,
          "price": 0.75,
          "halfPrice": 0,
          "position": 0,
          "isActive": false,
          "isDefault": false,
          "menuSubItem": {
            "menuSubItemId": 10951,
            "name": "Matcha Pudding",
            "price": 0,
            "displayDescription": "Matcha Pudding",
            "restaurantId": 55,
            "externalId": "3000037",
            "itemTypeId": 2,
            "isActive": false,
            "itemTypeName": "Option"
          }
        },
        {
          "menuSubItemGroupPriceId": 12055,
          "menuSubItemId": 11009,
          "menuSubItemGroupMenuSubItemGroupId": 1736,
          "price": 0.5,
          "halfPrice": 0,
          "position": 0,
          "isActive": false,
          "isDefault": false,
          "menuSubItem": {
            "menuSubItemId": 11009,
            "name": "Passion Fruit Jelly",
            "price": 0,
            "displayDescription": "Passion Fruit Jelly",
            "restaurantId": 55,
            "itemTypeId": 2,
            "isActive": true,
            "itemTypeName": "Option"
          }
        },
        {
          "menuSubItemGroupPriceId": 12056,
          "menuSubItemId": 10950,
          "menuSubItemGroupMenuSubItemGroupId": 1736,
          "price": 0.5,
          "halfPrice": 0,
          "position": 0,
          "isActive": false,
          "isDefault": false,
          "menuSubItem": {
            "menuSubItemId": 10950,
            "name": "Pineapple Jelly",
            "price": 0,
            "displayDescription": "Pineapple Jelly",
            "restaurantId": 55,
            "externalId": "3000045",
            "itemTypeId": 2,
            "isActive": false,
            "itemTypeName": "Option"
          }
        },
        {
          "menuSubItemGroupPriceId": 12057,
          "menuSubItemId": 10949,
          "menuSubItemGroupMenuSubItemGroupId": 1736,
          "price": 0.5,
          "halfPrice": 0,
          "position": 0,
          "isActive": false,
          "isDefault": false,
          "menuSubItem": {
            "menuSubItemId": 10949,
            "name": "Rainbow Jelly",
            "price": 0,
            "displayDescription": "Rainbow Jelly",
            "restaurantId": 55,
            "externalId": "3000021",
            "itemTypeId": 2,
            "isActive": false,
            "itemTypeName": "Option"
          }
        },
        {
          "menuSubItemGroupPriceId": 12058,
          "menuSubItemId": 10947,
          "menuSubItemGroupMenuSubItemGroupId": 1736,
          "price": 0.5,
          "halfPrice": 0,
          "position": 0,
          "isActive": false,
          "isDefault": false,
          "menuSubItem": {
            "menuSubItemId": 10947,
            "name": "Red Bean",
            "price": 0.5,
            "displayDescription": "Red Bean",
            "restaurantId": 55,
            "externalId": "3000019",
            "itemTypeId": 2,
            "isActive": false,
            "itemTypeName": "Option"
          }
        },
        {
          "menuSubItemGroupPriceId": 12059,
          "menuSubItemId": 11010,
          "menuSubItemGroupMenuSubItemGroupId": 1736,
          "price": 0.75,
          "halfPrice": 0,
          "position": 0,
          "isActive": false,
          "isDefault": false,
          "menuSubItem": {
            "menuSubItemId": 11010,
            "name": "Strawberry Popping Boba",
            "price": 0,
            "displayDescription": "Strawberry Popping Boba",
            "restaurantId": 55,
            "itemTypeId": 2,
            "isActive": true,
            "itemTypeName": "Option"
          }
        },
        {
          "menuSubItemGroupPriceId": 12060,
          "menuSubItemId": 10946,
          "menuSubItemGroupMenuSubItemGroupId": 1736,
          "price": 0.5,
          "halfPrice": 0,
          "position": 0,
          "isActive": false,
          "isDefault": false,
          "menuSubItem": {
            "menuSubItemId": 10946,
            "name": "Tofu Hua",
            "price": 0.5,
            "displayDescription": "Tofu Hua",
            "restaurantId": 55,
            "externalId": "3000018",
            "itemTypeId": 2,
            "isActive": false,
            "itemTypeName": "Option"
          }
        },
        {
          "menuSubItemGroupPriceId": 12235,
          "menuSubItemId": 10966,
          "menuSubItemGroupMenuSubItemGroupId": 1736,
          "price": 0.75,
          "halfPrice": 0,
          "position": 9999,
          "isActive": false,
          "isDefault": false,
          "menuSubItem": {
            "menuSubItemId": 10966,
            "name": "Peach Boba",
            "price": 0.75,
            "displayDescription": "Peach Boba",
            "restaurantId": 55,
            "externalId": "3000051",
            "itemTypeId": 2,
            "isActive": false,
            "itemTypeName": "Option"
          }
        },
        {
          "menuSubItemGroupPriceId": 12236,
          "menuSubItemId": 11127,
          "menuSubItemGroupMenuSubItemGroupId": 1736,
          "price": 0.75,
          "halfPrice": 0,
          "position": 9999,
          "isActive": false,
          "isDefault": false,
          "menuSubItem": {
            "menuSubItemId": 11127,
            "name": "Strawberry Heart Jelly",
            "price": 0,
            "displayDescription": "Strawberry Heart Jelly",
            "restaurantId": 55,
            "itemTypeId": 2,
            "isActive": true,
            "itemTypeName": "Option"
          }
        }
      ],
      "menuSubItems": [
        {
          "menuSubItemId": 10940,
          "name": "Agar Boba ",
          "price": 0,
          "description": "",
          "displayDescription": "Agar Boba ",
          "restaurantId": 55,
          "externalId": "3000036",
          "itemTypeId": 2,
          "isActive": false,
          "itemTypeName": "Option"
        },
        {
          "menuSubItemId": 10941,
          "name": "Aloe Vera",
          "price": 0,
          "description": "",
          "displayDescription": "Aloe Vera",
          "restaurantId": 55,
          "externalId": "3000016",
          "itemTypeId": 2,
          "isActive": false,
          "itemTypeName": "Option"
        },
        {
          "menuSubItemId": 10933,
          "name": "Boba",
          "price": 0,
          "description": "",
          "displayDescription": "Boba",
          "restaurantId": 55,
          "externalId": "3000009",
          "itemTypeId": 2,
          "isActive": false,
          "itemTypeName": "Option"
        },
        {
          "menuSubItemId": 10959,
          "name": "Chia Seed",
          "price": 0,
          "description": "",
          "displayDescription": "Chia Seed",
          "restaurantId": 55,
          "externalId": "3000035",
          "itemTypeId": 2,
          "isActive": false,
          "itemTypeName": "Option"
        },
        {
          "menuSubItemId": 10948,
          "name": "Coffee Jelly",
          "price": 0,
          "description": "",
          "displayDescription": "Coffee Jelly",
          "restaurantId": 55,
          "externalId": "3000015",
          "itemTypeId": 2,
          "isActive": false,
          "itemTypeName": "Option"
        },
        {
          "menuSubItemId": 10939,
          "name": "Egg Pudding",
          "price": 0,
          "description": "",
          "displayDescription": "Egg Pudding",
          "restaurantId": 55,
          "externalId": "3000010",
          "itemTypeId": 2,
          "isActive": false,
          "itemTypeName": "Option"
        },
        {
          "menuSubItemId": 10943,
          "name": "Grass Jelly",
          "price": 0,
          "description": "",
          "displayDescription": "Grass Jelly",
          "restaurantId": 55,
          "externalId": "3000012",
          "itemTypeId": 2,
          "isActive": false,
          "itemTypeName": "Option"
        },
        {
          "menuSubItemId": 10944,
          "name": "Litchi Jelly",
          "price": 0,
          "description": "",
          "displayDescription": "Litchi Jelly",
          "restaurantId": 55,
          "externalId": "3000014",
          "itemTypeId": 2,
          "isActive": false,
          "itemTypeName": "Option"
        },
        {
          "menuSubItemId": 10935,
          "name": "Mango Jelly",
          "price": 0,
          "description": "",
          "displayDescription": "Mango Jelly",
          "restaurantId": 55,
          "externalId": "3000031",
          "itemTypeId": 2,
          "isActive": false,
          "itemTypeName": "Option"
        },
        {
          "menuSubItemId": 11008,
          "name": "Mango Popping Boba",
          "price": 0,
          "description": "",
          "displayDescription": "Mango Popping Boba",
          "restaurantId": 55,
          "externalId": "",
          "itemTypeId": 2,
          "isActive": true,
          "itemTypeName": "Option"
        },
        {
          "menuSubItemId": 10952,
          "name": "Mango Pudding",
          "price": 0,
          "description": "",
          "displayDescription": "Mango Pudding",
          "restaurantId": 55,
          "externalId": "3000011",
          "itemTypeId": 2,
          "isActive": false,
          "itemTypeName": "Option"
        },
        {
          "menuSubItemId": 10951,
          "name": "Matcha Pudding",
          "price": 0,
          "description": "",
          "displayDescription": "Matcha Pudding",
          "restaurantId": 55,
          "externalId": "3000037",
          "itemTypeId": 2,
          "isActive": false,
          "itemTypeName": "Option"
        },
        {
          "menuSubItemId": 11009,
          "name": "Passion Fruit Jelly",
          "price": 0,
          "description": "",
          "displayDescription": "Passion Fruit Jelly",
          "restaurantId": 55,
          "externalId": "",
          "itemTypeId": 2,
          "isActive": true,
          "itemTypeName": "Option"
        },
        {
          "menuSubItemId": 10950,
          "name": "Pineapple Jelly",
          "price": 0,
          "description": "",
          "displayDescription": "Pineapple Jelly",
          "restaurantId": 55,
          "externalId": "3000045",
          "itemTypeId": 2,
          "isActive": false,
          "itemTypeName": "Option"
        },
        {
          "menuSubItemId": 10949,
          "name": "Rainbow Jelly",
          "price": 0,
          "description": "",
          "displayDescription": "Rainbow Jelly",
          "restaurantId": 55,
          "externalId": "3000021",
          "itemTypeId": 2,
          "isActive": false,
          "itemTypeName": "Option"
        },
        {
          "menuSubItemId": 10947,
          "name": "Red Bean",
          "price": 0,
          "description": "",
          "displayDescription": "Red Bean",
          "restaurantId": 55,
          "externalId": "3000019",
          "itemTypeId": 2,
          "isActive": false,
          "itemTypeName": "Option"
        },
        {
          "menuSubItemId": 11010,
          "name": "Strawberry Popping Boba",
          "price": 0,
          "description": "",
          "displayDescription": "Strawberry Popping Boba",
          "restaurantId": 55,
          "externalId": "",
          "itemTypeId": 2,
          "isActive": true,
          "itemTypeName": "Option"
        },
        {
          "menuSubItemId": 10946,
          "name": "Tofu Hua",
          "price": 0,
          "description": "",
          "displayDescription": "Tofu Hua",
          "restaurantId": 55,
          "externalId": "3000018",
          "itemTypeId": 2,
          "isActive": false,
          "itemTypeName": "Option"
        },
        {
          "menuSubItemId": 10966,
          "name": "Peach Boba",
          "price": 0,
          "description": "",
          "displayDescription": "Peach Boba",
          "restaurantId": 55,
          "externalId": "3000051",
          "itemTypeId": 2,
          "isActive": false,
          "itemTypeName": "Option"
        },
        {
          "menuSubItemId": 11127,
          "name": "Strawberry Heart Jelly",
          "price": 0,
          "description": "",
          "displayDescription": "Strawberry Heart Jelly",
          "restaurantId": 55,
          "externalId": "",
          "itemTypeId": 2,
          "isActive": true,
          "itemTypeName": "Option"
        }
      ]
    }
  ],
  "menuSubItemModifyPrices": [],
  "menuItemId": 12189,
  "name": "P2 Super Lime Sijichun",
  "description": "378 calories",
  "price": 5.25,
  "productImage": "/imagesmenu/P2-Super-Lime-Sijichun.jpg",
  "isPizza": false,
  "disableSpecialInstruction": false
}